nbsdata/__init__.py
nbsdata/asset/citycodes.csv
nbsdata/asset/indicator_csnd.csv
nbsdata/asset/indicator_csyd.csv
nbsdata/asset/indicator_fsjd.csv
nbsdata/asset/indicator_fsnd.csv
nbsdata/asset/indicator_fsyd.csv
nbsdata/asset/indicator_hgjd.csv
nbsdata/asset/indicator_hgnd.csv
nbsdata/asset/indicator_hgyd.csv
nbsdata/asset/provincecodes.csv
nbsdata-1.0.1.dist-info/licenses/LICENSE
nbsdata-1.0.1.dist-info/METADATA
nbsdata-1.0.1.dist-info/WHEEL
nbsdata-1.0.1.dist-info/top_level.txt
nbsdata-1.0.1.dist-info/RECORD
