Metadata-Version: 2.4
Name: nbsdata
Version: 1.0.1
Summary: Data from National Bureau of Statistics, China
Author-email: Rho Zhang <rhozhang@163.com>
License-Expression: MIT
Project-URL: Homepage, https://github.com/rhozhang/nbsdata
Project-URL: Issues, https://github.com/rhozhang/nbsdata/issues
Keywords: data,NBS,China,sn-stats
Classifier: Programming Language :: Python :: 3
Classifier: Operating System :: OS Independent
Classifier: Development Status :: 4 - Beta
Requires-Python: >=3.12
License-File: LICENSE
Requires-Dist: requests
Requires-Dist: polars
Dynamic: license-file
